model_field_meta/__init__.py
model_field_meta/fields.py
model_field_meta/mixins.py
model_field_meta/wrapper.py
tests/__init__.py
tests/models.py
tests/settings.py
tests/test_fields.py
tests/test_migration.py
tests/test_mixins.py
django_model_field_meta-0.6.dist-info/LICENSE
django_model_field_meta-0.6.dist-info/METADATA
django_model_field_meta-0.6.dist-info/WHEEL
django_model_field_meta-0.6.dist-info/top_level.txt
django_model_field_meta-0.6.dist-info/RECORD
