Metadata-Version: 2.1
Name: django-model-field-meta
Version: 0.6
Summary: Django model field metadata and utilities
Home-page: https://github.com/melvinkcx/django-model-field-meta
Author: Melvin Koh
Author-email: melvinkcx@gmail.com
License: UNKNOWN
Platform: UNKNOWN
Classifier: Development Status :: 5 - Production/Stable
Classifier: Environment :: Web Environment
Classifier: Intended Audience :: Developers
Classifier: License :: OSI Approved :: MIT License
Classifier: Operating System :: OS Independent
Classifier: Programming Language :: Python
Classifier: Programming Language :: Python :: 3
Classifier: Programming Language :: Python :: 3.7
Classifier: Programming Language :: Python :: 3.6
Classifier: Programming Language :: Python :: 3.5
Classifier: Framework :: Django
Classifier: Framework :: Django :: 2.1
Classifier: Framework :: Django :: 2.2
Requires-Python: >=3.0
